LICENSE.txt
README.md
setup.py
cellpylib/__init__.py
cellpylib/apen.py
cellpylib/bien.py
cellpylib/ca_functions.py
cellpylib/ca_functions2d.py
cellpylib/ctrbl_rule.py
cellpylib/entropy.py
cellpylib/evoloop.py
cellpylib/hopfield_net.py
cellpylib/langtons_loop.py
cellpylib/rule_tables.py
cellpylib/sandpile.py
cellpylib/sdsr_loop.py
cellpylib.egg-info/PKG-INFO
cellpylib.egg-info/SOURCES.txt
cellpylib.egg-info/dependency_links.txt
cellpylib.egg-info/requires.txt
cellpylib.egg-info/top_level.txt